thassault/__init__.py
thassault/cli.py
thassault/http.py
thassault/stats.py
thassault-0.1.0.dist-info/METADATA
thassault-0.1.0.dist-info/WHEEL
thassault-0.1.0.dist-info/entry_points.txt
thassault-0.1.0.dist-info/top_level.txt
thassault-0.1.0.dist-info/RECORD
