Metadata-Version: 2.1
Name: thassault
Version: 0.1.0
Summary: Application for retrieving web load statistics
Home-page: https://github.com/themisAnagno/thassault.git
Author: Themis Anagnostopoulos
Author-email: them.anagno@gmail.com
License: MIT
Platform: UNKNOWN
Classifier: License :: OSI Approved :: MIT License
Classifier: Programming Language :: Python
Classifier: Programming Language :: Python :: 3
Classifier: Programming Language :: Python :: 3.7
Classifier: Programming Language :: Python :: Implementation :: CPython
Classifier: Programming Language :: Python :: Implementation :: PyPy
Requires-Python: >=3.7.0
Requires-Dist: click
Requires-Dist: requests
